discord/ext/utils/__init__.py
discord/ext/utils/abc.py
discord/ext/utils/bot.py
discord/ext/utils/converters.py
discord/ext/utils/extra.py
discord_ext_utils-0.0.1.dist-info/LICENSE
discord_ext_utils-0.0.1.dist-info/METADATA
discord_ext_utils-0.0.1.dist-info/WHEEL
discord_ext_utils-0.0.1.dist-info/top_level.txt
discord_ext_utils-0.0.1.dist-info/RECORD
