Metadata-Version: 2.1
Name: discord-ext-utils
Version: 0.0.1
Summary: a collection of utils I use with discord.py
Home-page: https://github.com/cibere/discord-ext-utils
Author: cibere
Author-email: cibere.dev@gmail.com
License: MIT
Project-URL: Code, https://github.com/cibere/discord-ext-utils
Project-URL: Issue tracker, https://github.com/cibere/discord-ext-utils/issues
Project-URL: Discord/Support Server, https://discord.gg/2MRrJvP42N
Requires-Python: >=3.10
License-File: LICENSE
